{
  "lineInfo": [
    {
      "date": "2025-05-29T22:00:00.000Z",
      "volume": 2.407,
      "month1": 1.7325,
      "month2": 1.74,
      "month3": 1.7525,
      "month4": 1.7475,
      "month5": 1.73,
      "month6": 1.6925,
      "month7": 1.655,
      "month8": 1.63,
      "month9": 1.615,
      "month10": 1.6225,
      "month11": 1.6375,
      "month12": 1.66,
      "month13": 1.67,
      "month14": 1.675
    }
  ],
  "lineTmp": [
    {
      "date": "${table:CU.date}",
      "volume": "${table:CU.volume}",
      "month1": "${table:CU.month1}",
      "month2": "${table:CU.month2}",
      "month3": "${table:CU.month3}",
      "month4": "${table:CU.month4}",
      "month5": "${table:CU.month5}",
      "month6": "${table:CU.month6}",
      "month7": "${table:CU.month7}",
      "month8": "${table:CU.month8}",
      "month9": "${table:CU.month9}",
      "month10": "${table:CU.month10}",
      "month11": "${table:CU.month11}",
      "month12": "${table:CU.month12}",
      "month13": "${table:CU.month13}",
      "month14": "${table:CU.month14}"
    }
  ],
  "resume": [
    {
      "date": "2025-05-30 12:09:39",
      "tradeDate": "05/29/2025",
      "origin": "CMEGroup Chicago-CU",
      "amount": 14
    }
  ]
}